wormy/__init__.py
wormy-0.0.4.dist-info/LICENCE.txt
wormy-0.0.4.dist-info/METADATA
wormy-0.0.4.dist-info/WHEEL
wormy-0.0.4.dist-info/top_level.txt
wormy-0.0.4.dist-info/RECORD
