Metadata-Version: 2.1
Name: wormy
Version: 0.0.4
Summary: Basic Python module made by a middle schoool student for fun
Home-page: UNKNOWN
Author: Sahil
Author-email: smartluminous213@gmail.com
License: MIT
Platform: UNKNOWN
Classifier: Development Status :: 5 - Production/Stable
Classifier: Intended Audience :: Education
Classifier: Operating System :: Microsoft :: Windows :: Windows 10
Classifier: Programming Language :: Python
Classifier: License :: OSI Approved :: MIT License
Classifier: Programming Language :: Python :: 3
License-File: LICENCE.txt
